{
    "program_name": "41- ( IT2 ) CNTT: Kỹ thuật máy tính",
    "admission_code": "IT2",
    "overview": {
        "degree": "Cử nhân - Thạc sĩ tích hợp",
        "enrollment_time": "Tháng 8 hàng năm",
        "duration": "4 - 5,5 năm",
        "tuition": "22 - 28",
        "description": "Giới thiệu"
    },
    "training_program_summary": "Khối kiến thức đặc trưng Hệ thống máy tính, xử lý tín hiệu, cấu trúc dữ liệu và thuật toán, kỹ thuật lập trình, mạng truyền thông dữ liệu, phát triển hệ thống phần mềm, trí tuệ nhân tạo và học máy, an toàn thông tin; Phát triển các hệ thống, dịch vụ, giải pháp về Hệ thống nhúng và IoT, Mạng truyền thông dữ liệu thế hệ mới, An toàn không gian số. Thông tin chi tiết chương trình đào tạo - XEM TẠI ĐÂY Liên hệ tư vấn Điện thoại: 024 3 869 2463 Địa chỉ: Phòng 505, Toà nhà B1, ĐHBK Hà Nội Email: giangnl@soict.hust.edu.vn",
    "job_opportunities": [
        "Phát triển phần mềm cho các hệ thống tính toán, đặc biệt là các hệ thống vận hành trên nền mạng máy tính;",
        "Phát triển hệ thống nhúng thông minh, hệ thống mạng vạn vật (Internet of Things);",
        "Thiết kế, phát triển, triển khai, vận hành hệ thống giải pháp mạng truyền thông dữ liệu, giải pháp an toàn an ninh mạng truyền thông dữ liệu."
    ],
    "contact": {},
    "management_unit": {
        "name": "Trường Công nghệ thông tin và Truyền thông",
        "address": "Văn phòng Trường CNTT&TT (P505 - Nhà B1)",
        "hotline": "024 3869 2463",
        "email": "vp@soict.hust.edu.vn",
        "website": "https://soict.hust.edu.vn/"
    },
    "source_url": "https://ts.hust.edu.vn/training-cate/nganh-dao-tao-dai-hoc/cntt-ky-thuat-may-tinh"
}